PDFNetPython3-9.5.0.post2.data/purelib/PDFNetPython3/PDFNetC.dll
PDFNetPython3-9.5.0.post2.data/purelib/PDFNetPython3/PDFNetPyLibInfo
PDFNetPython3-9.5.0.post2.data/purelib/PDFNetPython3/PDFNetPython.py
PDFNetPython3-9.5.0.post2.data/purelib/PDFNetPython3/_PDFNetPython.pyd
PDFNetPython3-9.5.0.post2.data/purelib/PDFNetPython3/__init__.py
PDFNetPython3-9.5.0.post2.data/purelib/apryse_sdk_python3/PDFNetC.dll
PDFNetPython3-9.5.0.post2.data/purelib/apryse_sdk_python3/PDFNetPyLibInfo
PDFNetPython3-9.5.0.post2.data/purelib/apryse_sdk_python3/PDFNetPython.py
PDFNetPython3-9.5.0.post2.data/purelib/apryse_sdk_python3/_PDFNetPython.pyd
PDFNetPython3-9.5.0.post2.data/purelib/apryse_sdk_python3/__init__.py
PDFNetPython3-9.5.0.post2.dist-info/METADATA
PDFNetPython3-9.5.0.post2.dist-info/WHEEL
PDFNetPython3-9.5.0.post2.dist-info/license.pdf
PDFNetPython3-9.5.0.post2.dist-info/top_level.txt
PDFNetPython3-9.5.0.post2.dist-info/RECORD
