Metadata-Version: 2.1
Name: PDFNetPython3
Version: 9.5.0.post2
Summary: PDFNetPython3 Wrapper
Home-page: https://www.pdftron.com/documentation/python/get-started/python3
Author: PDFTron Systems Inc.
Author-email: support@pdftron.com
Maintainer: mnguyen
Maintainer-email: mnguyen@pdftron.com
License: Other/Proprietary License (Commercial)
Keywords: PDF SDK,PDF library,PDF toolkit,PDF convert,PDF render,PDF view,PDF print,edit PDF
Classifier: Development Status :: 5 - Production/Stable
Classifier: Intended Audience :: Developers
Classifier: License :: OSI Approved
Classifier: Programming Language :: Python
Classifier: Programming Language :: Python :: 3
Classifier: Programming Language :: Python :: 3.5
Classifier: Programming Language :: Python :: 3.6
Classifier: Programming Language :: Python :: 3.7
Classifier: Programming Language :: Python :: 3.8
Classifier: Programming Language :: Python :: 3.9
Classifier: Programming Language :: Python :: 3.10
Classifier: Programming Language :: Python :: 3.11
Classifier: Programming Language :: Python :: 3 :: Only
Classifier: Programming Language :: Python :: Implementation :: CPython
Classifier: Topic :: Software Development
Classifier: Operating System :: Microsoft :: Windows
Classifier: Operating System :: POSIX
Classifier: Operating System :: Unix
Classifier: Operating System :: MacOS
Requires-Python: >=3.5
License-File: license.pdf
